{
  "canton": "JU",
  "law_key": "ju-kv",
  "sr_number": "101",
  "language": "fr",
  "title": "SR Number:** 101",
  "lexfind_id": 8442,
  "fetched_at": "2026-04-14",
  "source": "mcp_lexfind_pdf",
  "article_count": 60,
  "articles": [
    {
      "number": 2,
      "suffix": "",
      "raw": "2",
      "title": "La souveraineté appartient au peuple, qui l'exerce directement ou par"
    },
    {
      "number": 3,
      "suffix": "",
      "raw": "3",
      "title": "Le français est la langue nationale et officielle de la République et"
    },
    {
      "number": 4,
      "suffix": "",
      "raw": "4",
      "title": "Coopération"
    },
    {
      "number": 5,
      "suffix": "",
      "raw": "5",
      "title": "Armoiries"
    },
    {
      "number": 6,
      "suffix": "",
      "raw": "6",
      "title": ""
    },
    {
      "number": 8,
      "suffix": "",
      "raw": "8",
      "title": "Libertés"
    },
    {
      "number": 9,
      "suffix": "",
      "raw": "9",
      "title": ""
    },
    {
      "number": 109,
      "suffix": "",
      "raw": "109",
      "title": ""
    },
    {
      "number": 11,
      "suffix": "",
      "raw": "11",
      "title": "Censure"
    },
    {
      "number": 12,
      "suffix": "",
      "raw": "12",
      "title": "Propriété"
    },
    {
      "number": 13,
      "suffix": "",
      "raw": "13",
      "title": "Les droits fondamentaux ne peuvent être limités que par la loi et dans"
    },
    {
      "number": 14,
      "suffix": "",
      "raw": "14",
      "title": ""
    },
    {
      "number": 15,
      "suffix": "",
      "raw": "15",
      "title": "Chacun est tenu d'accomplir ses devoirs légaux envers l'Etat et les"
    },
    {
      "number": 16,
      "suffix": "",
      "raw": "16",
      "title": "Droit de cité"
    },
    {
      "number": 17,
      "suffix": "",
      "raw": "17",
      "title": "La famille"
    },
    {
      "number": 18,
      "suffix": "",
      "raw": "18",
      "title": "Principe"
    },
    {
      "number": 19,
      "suffix": "",
      "raw": "19",
      "title": "Droit au travail"
    },
    {
      "number": 20,
      "suffix": "",
      "raw": "20",
      "title": ""
    },
    {
      "number": 21,
      "suffix": "",
      "raw": "21",
      "title": "L'Etat instaure un organe cantonal de conciliation et d'arbitrage"
    },
    {
      "number": 22,
      "suffix": "",
      "raw": "22",
      "title": ""
    },
    {
      "number": 23,
      "suffix": "",
      "raw": "23",
      "title": ""
    },
    {
      "number": 24,
      "suffix": "",
      "raw": "24",
      "title": "L'aide sociale"
    },
    {
      "number": 25,
      "suffix": "",
      "raw": "25",
      "title": ""
    },
    {
      "number": 264,
      "suffix": "",
      "raw": "264",
      "title": ""
    },
    {
      "number": 28,
      "suffix": "",
      "raw": "28",
      "title": "Police sanitaire"
    },
    {
      "number": 29,
      "suffix": "",
      "raw": "29",
      "title": "Assurances"
    },
    {
      "number": 30,
      "suffix": "",
      "raw": "30",
      "title": "Sport"
    },
    {
      "number": 31,
      "suffix": "",
      "raw": "31",
      "title": ""
    },
    {
      "number": 32,
      "suffix": "",
      "raw": "32",
      "title": "Mission"
    },
    {
      "number": 33,
      "suffix": "",
      "raw": "33",
      "title": "Obligation"
    },
    {
      "number": 35,
      "suffix": "",
      "raw": "35",
      "title": ""
    },
    {
      "number": 36,
      "suffix": "",
      "raw": "36",
      "title": "L'Etat entretient ou encourage les établissements spécialisés dans"
    },
    {
      "number": 37,
      "suffix": "",
      "raw": "37",
      "title": "L'Etat crée, au besoin par des conventions, la possibilité d'acquérir"
    },
    {
      "number": 38,
      "suffix": "",
      "raw": "38",
      "title": "Ecoles privées"
    },
    {
      "number": 39,
      "suffix": "",
      "raw": "39",
      "title": "Surveillance"
    },
    {
      "number": 40,
      "suffix": "",
      "raw": "40",
      "title": ""
    },
    {
      "number": 41,
      "suffix": "",
      "raw": "41",
      "title": "Conseil scolaire"
    },
    {
      "number": 42,
      "suffix": "",
      "raw": "42",
      "title": ""
    },
    {
      "number": 43,
      "suffix": "",
      "raw": "43",
      "title": ""
    },
    {
      "number": 44,
      "suffix": "",
      "raw": "44",
      "title": "L'Etat institue le Bureau de la condition féminine dont les tâches sont"
    },
    {
      "number": 45,
      "suffix": "",
      "raw": "45",
      "title": ""
    },
    {
      "number": 46,
      "suffix": "",
      "raw": "46",
      "title": ""
    },
    {
      "number": 47,
      "suffix": "",
      "raw": "47",
      "title": ""
    },
    {
      "number": 48,
      "suffix": "",
      "raw": "48",
      "title": ""
    },
    {
      "number": 49,
      "suffix": "",
      "raw": "49",
      "title": ""
    },
    {
      "number": 50,
      "suffix": "",
      "raw": "50",
      "title": ""
    },
    {
      "number": 52,
      "suffix": "",
      "raw": "52",
      "title": ""
    },
    {
      "number": 53,
      "suffix": "",
      "raw": "53",
      "title": "L'Etat encourage l'aide humanitaire et coopère au développement"
    },
    {
      "number": 54,
      "suffix": "",
      "raw": "54",
      "title": "L'Etat et les communes assurent l'ordre public, la sécurité et la"
    },
    {
      "number": 55,
      "suffix": "",
      "raw": "55",
      "title": ""
    },
    {
      "number": 56,
      "suffix": "",
      "raw": "56",
      "title": ""
    },
    {
      "number": 57,
      "suffix": "",
      "raw": "57",
      "title": "L'Etat et les communes répondent du dommage qu'autorités et"
    },
    {
      "number": 58,
      "suffix": "",
      "raw": "58",
      "title": "Les lois ne peuvent avoir d'effet rétroactif si elles imposent des"
    },
    {
      "number": 59,
      "suffix": "",
      "raw": "59",
      "title": ""
    },
    {
      "number": 60,
      "suffix": "",
      "raw": "60",
      "title": "La loi prévoit que des compétences dérogeant à la Constitution"
    },
    {
      "number": 61,
      "suffix": "",
      "raw": "61",
      "title": ""
    },
    {
      "number": 62,
      "suffix": "",
      "raw": "62",
      "title": ""
    },
    {
      "number": 63,
      "suffix": "",
      "raw": "63",
      "title": ""
    },
    {
      "number": 64,
      "suffix": "",
      "raw": "64",
      "title": "La charge de membre du Gouvernement ou de juge permanent est"
    },
    {
      "number": 65,
      "suffix": "",
      "raw": "65",
      "title": ""
    }
  ],
  "article_texts": {
    "2": [
      {
        "num": null,
        "text": "ses représentants."
      },
      {
        "num": null,
        "text": "Langue"
      }
    ],
    "3": [
      {
        "num": null,
        "text": "Canton du Jura. 101 2"
      }
    ],
    "4": [
      {
        "num": "1",
        "text": "La République et Canton du Jura collabore avec les autres cantons de la Confédération suisse."
      },
      {
        "num": "2",
        "text": "Elle s'efforce d'assurer une coopération étroite avec ses voisins."
      },
      {
        "num": "3",
        "text": "Elle est ouverte au monde et coopère avec les peuples soucieux de solidarité."
      }
    ],
    "5": [
      {
        "num": null,
        "text": "Les armoiries de la République et Canton du Jura sont les suivantes : \"Parti d'argent à la crosse épiscopale de gueules et de gueules à trois fasces d'argent.\""
      },
      {
        "num": null,
        "text": "II.  LES DROITS FONDAMENTAUX"
      },
      {
        "num": null,
        "text": "Egalité devant la loi"
      }
    ],
    "6": [
      {
        "num": "1",
        "text": "Hommes et femmes sont égaux en droit."
      },
      {
        "num": "2",
        "text": "Nul ne doit subir préjudice ni tirer avantage du fait de sa naissance, de son origine, de sa race, de ses convictions, de ses opinions ou de sa situation sociale."
      },
      {
        "num": null,
        "text": "Dignité humaine Art. 7  1 La dignité humaine est intangible."
      },
      {
        "num": "2",
        "text": "Tout être humain a droit au libre développement de sa personnalité et à l'égalité des chances."
      }
    ],
    "8": [
      {
        "num": null,
        "text": "La liberté individuelle est garantie."
      },
      {
        "num": null,
        "text": "Le sont notamment :"
      },
      {
        "num": null,
        "text": "a) le droit à la vie et à l'intégrité physique et morale; b) le droit au respect de la vie privée et du domicile; c) le droit de contracter mariage et celui d'avoir une vie de famille; d) le droit d'élever et d'éduquer ses enfants; e) la liberté de pensée, de conscience et de religion; f) la liberté d'avoir, d'exprimer et de diffuser des opinions, en particulier la liberté de presse; g) la liberté d'association, de réunion et de manifestation publique; h) la liberté d'étude et d'enseignement; i) la liberté de l'art et de la recherche; j) la liberté de choisir et d'exercer une profession; 101 3 k) la liberté de commerce et d'industrie; l) la liberté d'établissement; m) la liberté d'accéder aux charges publiques."
      },
      {
        "num": null,
        "text": "Protection juridique en général"
      }
    ],
    "9": [
      {
        "num": "1",
        "text": "Nul ne peut être soustrait à son juge naturel."
      },
      {
        "num": "2",
        "text": "Toute partie doit être entendue avant qu'il soit statué sur sa cause."
      },
      {
        "num": "3",
        "text": "Chacun a le droit de consulter le dossier de sa cause, sauf dans les cas prévus par la loi."
      },
      {
        "num": "4",
        "text": "Les parties dépourvues des ressources nécessaires ont droit à l'assistance judiciaire gratuite selon la loi."
      }
    ],
    "109": [
      {
        "num": null,
        "text": ")"
      }
    ],
    "11": [
      {
        "num": null,
        "text": "La censure est interdite."
      }
    ],
    "12": [
      {
        "num": "1",
        "text": "La propriété, reconnue dans sa fonction privée et dans sa fonction sociale, est garantie dans les limites de la loi."
      },
      {
        "num": "2",
        "text": "L'expropriation donne droit à une juste indemnité, si possible préalable."
      },
      {
        "num": "3",
        "text": "Dans un intérêt public prépondérant, l'Etat prend des mesures pour empêcher l'exercice abusif de la propriété, notamment quant au sol, aux habitations et aux moyens de production importants."
      },
      {
        "num": "4",
        "text": "L'Etat favorise l'accession des agriculteurs à la propriété foncière rurale."
      },
      {
        "num": "5",
        "text": "La loi peut conférer un droit de préemption à l'Etat et aux communes lorsqu'un intérêt public prépondérant l'exige."
      },
      {
        "num": null,
        "text": "Limites des droits fondamentaux"
      }
    ],
    "13": [
      {
        "num": null,
        "text": "la seule mesure d'un intérêt public prépondérant."
      },
      {
        "num": null,
        "text": "Effets des droits fondamentaux"
      }
    ],
    "14": [
      {
        "num": "1",
        "text": "Tout pouvoir public est limité par les droits fondamentaux."
      },
      {
        "num": "2",
        "text": "Chacun exerce ses droits fondamentaux en respectant ceux d'autrui. 101 4"
      },
      {
        "num": null,
        "text": "Devoirs"
      }
    ],
    "15": [
      {
        "num": null,
        "text": "communes."
      }
    ],
    "16": [
      {
        "num": "1",
        "text": "La loi règle les conditions et la procédure d'acquisition du droit de cité cantonal et communal."
      },
      {
        "num": "2",
        "text": "Le droit de cité communal fonde la citoyenneté cantonale."
      },
      {
        "num": null,
        "text": "III.  LES TACHES DE L'ETAT 1. La famille"
      }
    ],
    "17": [
      {
        "num": "1",
        "text": "L'Etat protège et soutient la famille, cellule naturelle et fondamentale de la société."
      },
      {
        "num": "2",
        "text": "Il en renforce le rôle dans la communauté. 2. La sécurité sociale"
      }
    ],
    "18": [
      {
        "num": "1",
        "text": "L'Etat et les communes favorisent le bien-être général et la sécurité sociale."
      },
      {
        "num": "2",
        "text": "Ils protègent en particulier les personnes qui ont besoin d'aide en raison de leur âge, de leur santé et de leur situation économique ou sociale."
      },
      {
        "num": "3",
        "text": "Ils encouragent l'insertion des migrants dans le milieu social jurassien."
      }
    ],
    "19": [
      {
        "num": "1",
        "text": "Le droit au travail est reconnu."
      },
      {
        "num": "2",
        "text": "Avec le concours des communes, l'Etat s'efforce de promouvoir le plein emploi."
      },
      {
        "num": "3",
        "text": "Chaque travailleur a droit au salaire qui lui assure un niveau de vie décent."
      },
      {
        "num": "4",
        "text": "L'Etat encourage le reclassement professionnel."
      },
      {
        "num": "5",
        "text": "Il favorise l'intégration économique et sociale des handicapés. 101 5"
      },
      {
        "num": null,
        "text": "Protection des travailleurs"
      }
    ],
    "20": [
      {
        "num": null,
        "text": "Pour assurer la protection des travailleurs, l'Etat :"
      },
      {
        "num": null,
        "text": "a) organise l'assurance chômage obligatoire; b) institue la médecine du travail; c) légifère sur les conditions de travail; d) favorise la participation des travailleurs au sein des entreprises; e) protège les travailleurs et leurs représentants dans l'exercice de leurs droits; f) veille à l'application du principe \"à travail égal, salaire égal\"; g) reconnaît le droit de grève; la loi détermine les services publics où il peut être réglementé."
      },
      {
        "num": null,
        "text": "Paix sociale"
      }
    ],
    "21": [
      {
        "num": null,
        "text": "chargé d'intervenir dans les conflits sociaux."
      },
      {
        "num": null,
        "text": "Droit au logement"
      }
    ],
    "22": [
      {
        "num": "1",
        "text": "Le droit au logement est reconnu."
      },
      {
        "num": "2",
        "text": "L'Etat et les communes veillent à ce que toute personne obtienne, à des conditions raisonnables, un logement approprié."
      },
      {
        "num": "3",
        "text": "Ils prennent des mesures aux fins de protéger les locataires contre les abus."
      },
      {
        "num": null,
        "text": "Assurances et prestations sociales"
      }
    ],
    "23": [
      {
        "num": "1",
        "text": "L'Etat et les communes peuvent compléter les assurances et prestations sociales de la Confédération et en créer d'autres."
      },
      {
        "num": "2",
        "text": "L'Etat généralise les allocations familiales."
      },
      {
        "num": "3",
        "text": "Pour le financement des assurances et prestations sociales, la loi s'inspire du principe de la solidarité. 3. L'aide sociale"
      }
    ],
    "24": [
      {
        "num": null,
        "text": "L'aide sociale incombe à l'Etat et aux communes. 4. La santé publique"
      },
      {
        "num": null,
        "text": "Protection générale"
      }
    ],
    "25": [
      {
        "num": "1",
        "text": "L'Etat et les communes veillent à l'hygiène et à la santé publiques."
      },
      {
        "num": "2",
        "text": "Ils favorisent la médecine préventive et encouragent les activités visant à donner des soins aux malades et aux handicapés. 101 6"
      },
      {
        "num": "3",
        "text": "L'Etat règle et contrôle l'exercice des professions médicales et paramédicales."
      },
      {
        "num": null,
        "text": "Organisation du système hospitalier"
      }
    ],
    "264": [
      {
        "num": null,
        "text": ")  1 L'Etat organise et coordonne l'ensemble du système hospitalier et des services médicaux annexes."
      },
      {
        "num": "2",
        "text": "Il pourvoit à leur entretien.6)"
      },
      {
        "num": "3",
        "text": "Il en confie la gestion à un établissement de droit public."
      },
      {
        "num": null,
        "text": "Soins à domicile Art. 27  L'Etat favorise les soins à domicile."
      }
    ],
    "28": [
      {
        "num": null,
        "text": "L'Etat organise la police sanitaire."
      }
    ],
    "29": [
      {
        "num": "1",
        "text": "Sont obligatoires les assurances en cas de maladie, d'accident et de maternité."
      },
      {
        "num": "2",
        "text": "L'Etat favorise la prise en charge du coût des soins dentaires par l'assurance maladie."
      }
    ],
    "30": [
      {
        "num": null,
        "text": "L'Etat encourage la pratique générale du sport."
      },
      {
        "num": null,
        "text": "Conseil de la santé publique"
      }
    ],
    "31": [
      {
        "num": "1",
        "text": "L'Etat institue le Conseil de la santé publique."
      },
      {
        "num": "2",
        "text": "La loi en règle la composition, le fonctionnement et les compétences. 5. L'école"
      }
    ],
    "32": [
      {
        "num": "1",
        "text": "L'école a mission d'assurer aux enfants leur plein épanouissement."
      },
      {
        "num": "2",
        "text": "Elle assume, solidairement avec la famille, leur éducation et leur instruction."
      },
      {
        "num": "3",
        "text": "Elle forme des êtres libres, conscients de leurs responsabilités et capables de prendre en charge leur propre destinée."
      }
    ],
    "33": [
      {
        "num": null,
        "text": "L'école est obligatoire. 101 7"
      },
      {
        "num": null,
        "text": "Ecoles publiques Art. 34  1 L'Etat organise et contrôle l'école publique."
      },
      {
        "num": "2",
        "text": "L'accès à l'école maternelle est garanti."
      },
      {
        "num": "3",
        "text": "L'enseignement est gratuit."
      },
      {
        "num": "4",
        "text": "L'école publique respecte la liberté de pensée, de conscience et de religion."
      },
      {
        "num": null,
        "text": "Répartition des tâches"
      }
    ],
    "35": [
      {
        "num": "1",
        "text": "L'école maternelle et l'école obligatoire incombent à l'Etat et aux communes."
      },
      {
        "num": "2",
        "text": "Les lycées, les écoles professionnelles, les écoles de métiers et les écoles de commerce sont du ressort de l'Etat."
      },
      {
        "num": "3",
        "text": "Dans certains cas, la formation professionnelle peut être confiée à des institutions privées."
      },
      {
        "num": "4",
        "text": "L'Etat assume la formation initiale et permanente du corps enseignant."
      },
      {
        "num": null,
        "text": "Formation des handicapés"
      }
    ],
    "36": [
      {
        "num": null,
        "text": "lesquels les handicapés reçoivent une formation adaptée à leur état."
      },
      {
        "num": null,
        "text": "Formation hors du Canton"
      }
    ],
    "37": [
      {
        "num": null,
        "text": "certaines formations qui ne sont pas dispensées dans le Canton."
      }
    ],
    "38": [
      {
        "num": "1",
        "text": "Le droit d'ouvrir des écoles privées est garanti dans les limites de la loi."
      },
      {
        "num": "2",
        "text": "L'Etat soutient les écoles privées aux conditions fixées par la loi."
      }
    ],
    "39": [
      {
        "num": null,
        "text": "Toutes les écoles sont placées sous la surveillance de l'Etat."
      },
      {
        "num": null,
        "text": "Droit à la formation"
      }
    ],
    "40": [
      {
        "num": "1",
        "text": "Le droit à la formation est reconnu."
      },
      {
        "num": "2",
        "text": "L'Etat et les communes facilitent la fréquentation des écoles et des universités, ainsi que la formation professionnelle en général. 101 8"
      }
    ],
    "41": [
      {
        "num": "1",
        "text": "L'Etat institue le Conseil scolaire."
      },
      {
        "num": "2",
        "text": "La loi en règle la composition, le fonctionnement et les compétences. 6. La culture et l'éducation des adultes"
      },
      {
        "num": null,
        "text": "Activités culturelles"
      }
    ],
    "42": [
      {
        "num": "1",
        "text": "L'Etat et les communes soutiennent les activités culturelles dans le domaine de la création, de la recherche, de l'animation et de la diffusion."
      },
      {
        "num": "2",
        "text": "Ils veillent et contribuent à la conservation, à l'enrichissement et à la mise en valeur du patrimoine jurassien, notamment du patois."
      },
      {
        "num": "3",
        "text": "Ils favorisent l'illustration de la langue française."
      },
      {
        "num": null,
        "text": "Education des adultes"
      }
    ],
    "43": [
      {
        "num": null,
        "text": "L'Etat et les communes encouragent l'éducation des adultes. 7. Le Bureau de la condition féminine"
      },
      {
        "num": null,
        "text": "Le Bureau de la condition féminine"
      }
    ],
    "44": [
      {
        "num": null,
        "text": "notamment :"
      },
      {
        "num": null,
        "text": "a) améliorer la condition féminine; b) favoriser l'accès de la femme à tous les degrés de responsabilité; c) éliminer les discriminations dont elle peut faire l'objet. 7bis. Le développement durable11)"
      },
      {
        "num": null,
        "text": "Développement durable"
      },
      {
        "num": null,
        "text": "Art. 44a11)  1 L'Etat et les communes veillent à l'équilibre entre la préservation de l'environnement naturel et les exigences de la vie économique et sociale."
      },
      {
        "num": "2",
        "text": "Dans l'accomplissement de leurs tâches, ils respectent les principes du développement durable et prennent en compte les intérêts des générations futures. 101 9 8. L'environnement et le territoire"
      },
      {
        "num": null,
        "text": "Protection de l'environnement"
      }
    ],
    "45": [
      {
        "num": "1",
        "text": "L'Etat et les communes protègent l'homme et son milieu naturel contre les nuisances; ils combattent en particulier la pollution de l'air, du sol, de l'eau, ainsi que le bruit."
      },
      {
        "num": "2",
        "text": "Ils sauvegardent la beauté et l'originalité des paysages, de même que le patrimoine naturel et architectural."
      },
      {
        "num": "3",
        "text": "L'Etat protège la faune et la flore, notamment la forêt."
      },
      {
        "num": "4",
        "text": "Il règle la pratique de la chasse et de la pêche."
      },
      {
        "num": null,
        "text": "Aménagement du territoire"
      }
    ],
    "46": [
      {
        "num": "1",
        "text": "L'Etat et les communes assurent une utilisation judicieuse du sol et une occupation rationnelle du territoire."
      },
      {
        "num": "2",
        "text": "Ils sauvegardent dans la mesure du possible l'aire forestière et l'aire agricole, où la sylviculture et l'agriculture demeurent prioritaires."
      },
      {
        "num": "3",
        "text": "Ils réservent les espaces nécessaires au développement de l'économie et des voies de communication."
      },
      {
        "num": "4",
        "text": "Ils s'efforcent de ménager à l'usage commun les lieux particulièrement favorables à la santé et aux loisirs."
      },
      {
        "num": "5",
        "text": "Ils considèrent l'avis des populations en cause. 9. L'économie"
      },
      {
        "num": null,
        "text": "Développement de l'économie"
      }
    ],
    "47": [
      {
        "num": "1",
        "text": "L'Etat encourage le développement économique du Canton; il tient compte des besoins des régions et veille à la diversification des activités."
      },
      {
        "num": "2",
        "text": "Il peut, à cet effet, créer des services et soutenir des institutions, notamment un Conseil économique et social consultatif et un Office de développement économique."
      },
      {
        "num": null,
        "text": "Constructions et routes"
      }
    ],
    "48": [
      {
        "num": null,
        "text": "L'Etat légifère en matière de constructions et de routes. 101 10"
      },
      {
        "num": null,
        "text": "Transports publics"
      }
    ],
    "49": [
      {
        "num": null,
        "text": "L'Etat favorise les transports publics."
      },
      {
        "num": null,
        "text": "Ressources naturelles"
      }
    ],
    "50": [
      {
        "num": null,
        "text": "L'Etat contrôle l'exploitation des ressources naturelles."
      },
      {
        "num": null,
        "text": "Politique agricole Art. 51  L'Etat définit une politique agricole. 10. La protection des consommateurs"
      },
      {
        "num": null,
        "text": "La protection des consommateurs"
      }
    ],
    "52": [
      {
        "num": null,
        "text": "L'Etat considère les intérêts des consommateurs. 11. L'aide humanitaire"
      },
      {
        "num": null,
        "text": "L'aide humanitaire"
      }
    ],
    "53": [
      {
        "num": null,
        "text": "des peuples défavorisés. 12. L'ordre public"
      },
      {
        "num": null,
        "text": "L'ordre public"
      }
    ],
    "54": [
      {
        "num": null,
        "text": "tranquillité."
      },
      {
        "num": null,
        "text": "IV. L'ORGANISATION DE L'ETAT 1. Principes généraux"
      },
      {
        "num": null,
        "text": "Séparation des pouvoirs"
      }
    ],
    "55": [
      {
        "num": null,
        "text": "Les pouvoirs législatif, exécutif et judiciaire sont séparés."
      },
      {
        "num": null,
        "text": "Fondement des actes publics"
      }
    ],
    "56": [
      {
        "num": "1",
        "text": "Tout acte de l'autorité doit être fondé sur les principes du droit et de la bonne foi."
      },
      {
        "num": "2",
        "text": "Il doit être approprié à son but."
      },
      {
        "num": null,
        "text": "Responsabilité"
      }
    ],
    "57": [
      {
        "num": null,
        "text": "fonctionnaires causent, sans droit, dans l'exercice de leurs fonctions. 101 11"
      },
      {
        "num": null,
        "text": "Rétroactivité des lois"
      }
    ],
    "58": [
      {
        "num": null,
        "text": "charges ou obligations nouvelles aux particuliers ou aux communes."
      },
      {
        "num": null,
        "text": "Délégation de compétences"
      }
    ],
    "59": [
      {
        "num": "1",
        "text": "Le peuple, le Parlement et le Gouvernement peuvent déléguer leurs compétences aux termes de la loi."
      },
      {
        "num": "2",
        "text": "S'agissant du peuple et du Parlement, la loi limite l'objet de chaque délégation et en précise le but et la portée."
      },
      {
        "num": null,
        "text": "Droit de nécessité"
      }
    ],
    "60": [
      {
        "num": null,
        "text": "peuvent, en cas de guerre ou de catastrophe, être conférées temporairement au Parlement ou au Gouvernement."
      },
      {
        "num": null,
        "text": "Renseignements juridiques et médiation"
      }
    ],
    "61": [
      {
        "num": "1",
        "text": "L'Etat organise un service de renseignements juridiques en principe gratuit."
      },
      {
        "num": "2",
        "text": "Il peut instituer un organe indépendant de médiation en matière administrative."
      },
      {
        "num": null,
        "text": "Fonctions incompatibles"
      }
    ],
    "62": [
      {
        "num": "1",
        "text": "Nul ne peut exercer simultanément deux des fonctions suivantes : député au Parlement, membre du Gouvernement, juge permanent, procureur."
      },
      {
        "num": "2",
        "text": "Les membres du Gouvernement ne peuvent appartenir à une autorité de district ou de commune."
      },
      {
        "num": "3",
        "text": "Les juges permanents ne peuvent faire partie d'une autorité communale ou d'une autre autorité de district."
      },
      {
        "num": "4",
        "text": "Le mandat de parlementaire fédéral est incompatible avec les fonctions suivantes : député au parlement cantonal, juge permanent, procureur et membre du Gouvernement.3)"
      },
      {
        "num": "5",
        "text": "...3)"
      },
      {
        "num": "6",
        "text": "La loi règle les cas d'incompatibilité s'agissant des juges non permanents et des fonctionnaires."
      },
      {
        "num": null,
        "text": "Incompatibilité entre parents"
      }
    ],
    "63": [
      {
        "num": null,
        "text": "La loi règle les incompatibilités de fonctions entre parents et alliés. 101 12"
      },
      {
        "num": null,
        "text": "Double activité"
      }
    ],
    "64": [
      {
        "num": null,
        "text": "incompatible avec toute autre activité rétribuée."
      },
      {
        "num": null,
        "text": "Durée des fonctions"
      }
    ],
    "65": [
      {
        "num": "1",
        "text": "Les députés, les membres du Gouvernement, les juges, les procureurs et les membres des autorités de district et de commune sont élus pour cinq ans.8)"
      },
      {
        "num": "2",
        "text": "Les présidents et vice-présidents du Parlement, du Gouvernement et du"
      },
      {
        "num": null,
        "text": "Tribunal cantonal sont élus pour un an."
      },
      {
        "num": "3",
        "text": "Toute personne élue en cours de période exerce son mandat jusqu'à la fin de celle-ci. _… 85 more articles not shown. Total text length: 51,527 chars._"
      }
    ]
  }
}
